i_distributions/Binomialdistribution.py
i_distributions/Gaussiandistribution.py
i_distributions/Generaldistribution.py
i_distributions/__init__.py
i_distributions-0.1.dist-info/DESCRIPTION.rst
i_distributions-0.1.dist-info/METADATA
i_distributions-0.1.dist-info/RECORD
i_distributions-0.1.dist-info/WHEEL
i_distributions-0.1.dist-info/metadata.json
i_distributions-0.1.dist-info/top_level.txt
